jupyterpc/__init__.py
jupyterpc/jupyterpc.py
jupyterpc-0.1.8.dist-info/DESCRIPTION.rst
jupyterpc-0.1.8.dist-info/METADATA
jupyterpc-0.1.8.dist-info/RECORD
jupyterpc-0.1.8.dist-info/WHEEL
jupyterpc-0.1.8.dist-info/metadata.json
jupyterpc-0.1.8.dist-info/top_level.txt
