Metadata-Version: 2.0
Name: jupyterpc
Version: 0.1.8
Summary: Some Functions for making Tables and Graphics in Jupyter
Home-page: https://github.com/phil1425/jupyter-pc
Author: Philipp Kollenz
Author-email: philipp.kollenz@bombombox.net
License: MIT
Platform: UNKNOWN
Requires-Dist: uncertainties
Requires-Dist: scipy
Requires-Dist: jinja2
Requires-Dist: numpy
